dwca/__init__.py
dwca/descriptors.py
dwca/exceptions.py
dwca/files.py
dwca/helpers.py
dwca/minibench.py
dwca/read.py
dwca/rows.py
dwca/star_record.py
dwca/vendor.py
dwca/version.py
dwca/darwincore/__init__.py
dwca/darwincore/build_dc_terms_list.py
dwca/darwincore/terms.py
dwca/darwincore/utils.py
dwca/test/__init__.py
dwca/test/helpers.py
dwca/test/test_datafile.py
dwca/test/test_descriptors.py
dwca/test/test_dwcareader.py
dwca/test/test_rows.py
dwca/test/test_star_record.py
python_dwca_reader-0.16.4.dist-info/AUTHORS
python_dwca_reader-0.16.4.dist-info/LICENSE.txt
python_dwca_reader-0.16.4.dist-info/METADATA
python_dwca_reader-0.16.4.dist-info/WHEEL
python_dwca_reader-0.16.4.dist-info/top_level.txt
python_dwca_reader-0.16.4.dist-info/RECORD
