Metadata-Version: 2.1
Name: python-dwca-reader
Version: 0.16.4
Summary: A simple Python package to read Darwin Core Archive (DwC-A) files.
Home-page: https://github.com/BelgianBiodiversityPlatform/python-dwca-reader
Author: Nicolas Noé - Belgian Biodiversity Platform
Author-email: n.noe@biodiversity.be
License: BSD licence, see LICENCE.txt
Classifier: Programming Language :: Python :: 3
Classifier: Programming Language :: Python :: 3.7
Classifier: Programming Language :: Python :: 3.8
Classifier: Programming Language :: Python :: 3.9
Classifier: Programming Language :: Python :: 3.10
Classifier: Programming Language :: Python :: 3.11
Classifier: Programming Language :: Python :: Implementation :: PyPy
License-File: LICENSE.txt
License-File: AUTHORS
